tree_matching_distance/__init__.py
tree_matching_distance/main.py
tree_matching_distance-1.0.7.dist-info/METADATA
tree_matching_distance-1.0.7.dist-info/RECORD
tree_matching_distance-1.0.7.dist-info/WHEEL
tree_matching_distance-1.0.7.dist-info/entry_points.txt
tree_matching_distance-1.0.7.dist-info/top_level.txt
