Metadata-Version: 2.1
Name: tree-matching-distance
Version: 1.0.7
Summary: Compute tree distance using a method by Lin et al
Home-page: https://github.com/arvestad/tree_matching_distance
Author: Lars Arvestad
Author-email: arve@math.su.se
License: gpl3
Project-URL: Documentation, https://github.com/arvestad/tree_matching_distance
Platform: any
Classifier: Development Status :: 5 - Production/Stable
Classifier: Programming Language :: Python :: 3
Classifier: License :: OSI Approved :: GNU General Public License v3 (GPLv3)
Classifier: Operating System :: OS Independent
Classifier: Topic :: Scientific/Engineering :: Bio-Informatics
Requires-Dist: ete3
Requires-Dist: networkx
